{"users": [{"id": 2601874716, "id_str": "2601874716", "name": "getstream.io", "screen_name": "getstream_io", "location": "Boulder, CO", "description": "Techstars NYC 2015 - Build scalable feeds, activity streams & chat in a few hours instead of weeks. Boulder & Amsterdam. Get started at https://t.co/VeA0L3D5vl!", "url": "https://t.co/CwLyOnt1xx", "entities": {"url": {"urls": [{"url": "https://t.co/CwLyOnt1xx", "expanded_url": "http://getstream.io/", "display_url": "getstream.io", "indices": [0, 23]}]}, "description": {"urls": [{"url": "https://t.co/VeA0L3D5vl", "expanded_url": "https://getstream.io", "display_url": "getstream.io", "indices": [136, 159]}]}}, "protected": false, "followers_count": 6597, "friends_count": 3218, "listed_count": 156, "created_at": "Thu Jul 03 16:11:09 +0000 2014", "favourites_count": 335, "utc_offset": null, "time_zone": null, "geo_enabled": true, "verified": false, "statuses_count": 845, "lang": null, "status": {"created_at": "Fri Sep 06 21:32:53 +0000 2019", "id": 1170087498111840257, "id_str": "1170087498111840257", "text": "Happiest of Birthdays to our CSO, @scottlasica! Yes, those are deviled birthday eggs. \ud83d\ude02 #ketolife https://t.co/92G16iBARC", "truncated": false, "entities": {"hashtags": [{"text": "ketolife", "indices": [88, 97]}], "symbols": [], "user_mentions": [{"screen_name": "scottlasica", "name": "Young Shatner", "id": 14183770, "id_str": "14183770", "indices": [34, 46]}], "urls": [], "media": [{"id": 1170087492843819008, "id_str": "1170087492843819008", "indices": [98, 121], "media_url": "http://pbs.twimg.com/media/EDz8YBcVUAAJnYy.jpg", "media_url_https": "https://pbs.twimg.com/media/EDz8YBcVUAAJnYy.jpg", "url": "https://t.co/92G16iBARC", "display_url": "pic.twitter.com/92G16iBARC", "expanded_url": "https://twitter.com/getstream_io/status/1170087498111840257/photo/1", "type": "photo", "sizes": {"medium": {"w": 1200, "h": 896, "resize": "fit"}, "large": {"w": 2048, "h": 1530, "resize": "fit"}, "thumb": {"w": 150, "h": 150, "resize": "crop"}, "small": {"w": 680, "h": 508, "resize": "fit"}}}]}, "extended_entities": {"media": [{"id": 1170087492843819008, "id_str": "1170087492843819008", "indices": [98, 121], "media_url": "http://pbs.twimg.com/media/EDz8YBcVUAAJnYy.jpg", "media_url_https": "https://pbs.twimg.com/media/EDz8YBcVUAAJnYy.jpg", "url": "https://t.co/92G16iBARC", "display_url": "pic.twitter.com/92G16iBARC", "expanded_url": "https://twitter.com/getstream_io/status/1170087498111840257/photo/1", "type": "photo", "sizes": {"medium": {"w": 1200, "h": 896, "resize": "fit"}, "large": {"w": 2048, "h": 1530, "resize": "fit"}, "thumb": {"w": 150, "h": 150, "resize": "crop"}, "small": {"w": 680, "h": 508, "resize": "fit"}}}]}, "source": "<a href=\"http://twitter.com/download/iphone\" rel=\"nofollow\">Twitter for iPhone</a>", "in_reply_to_status_id": null, "in_reply_to_status_id_str": null, "in_reply_to_user_id": null, "in_reply_to_user_id_str": null, "in_reply_to_screen_name": null, "geo": null, "coordinates": null, "place": {"id": "fd70c22040963ac7", "url": "https://api.twitter.com/1.1/geo/id/fd70c22040963ac7.json", "place_type": "city", "name": "Boulder", "full_name": "Boulder, CO", "country_code": "US", "country": "United States", "contained_within": [], "bounding_box": {"type": "Polygon", "coordinates": [[[-105.3017759, 39.953552], [-105.183597, 39.953552], [-105.183597, 40.094411], [-105.3017759, 40.094411]]]}, "attributes": {}}, "contributors": null, "is_quote_status": false, "retweet_count": 1, "favorite_count": 2, "favorited": false, "retweeted": false, "possibly_sensitive": false, "lang": "en"}, "contributors_enabled": false, "is_translator": false, "is_translation_enabled": false, "profile_background_color": "000000", "profile_background_image_url": "http://abs.twimg.com/images/themes/theme1/bg.png", "profile_background_image_url_https": "https://abs.twimg.com/images/themes/theme1/bg.png", "profile_background_tile": false, "profile_image_url": "http://pbs.twimg.com/profile_images/735113666891128833/mBSAJI_h_normal.jpg", "profile_image_url_https": "https://pbs.twimg.com/profile_images/735113666891128833/mBSAJI_h_normal.jpg", "profile_banner_url": "https://pbs.twimg.com/profile_banners/2601874716/1464211135", "profile_link_color": "2F7DEA", "profile_sidebar_border_color": "000000", "profile_sidebar_fill_color": "000000", "profile_text_color": "000000", "profile_use_background_image": false, "has_extended_profile": true, "default_profile": false, "default_profile_image": false, "following": true, "live_following": false, "follow_request_sent": false, "notifications": false, "muting": false, "blocking": false, "blocked_by": false, "translator_type": "none"}, {"id": 15444168, "id_str": "15444168", "name": "Open Book", "screen_name": "OpenBookON", "location": "Ontario, Canada", "description": "Open Book is your connection to Toronto's vibrant literary scene. Tweets via Holly, Grace, and Kevin.", "url": "https://t.co/PpdhoZ19i3", "entities": {"url": {"urls": [{"url": "https://t.co/PpdhoZ19i3", "expanded_url": "http://www.open-book.ca", "display_url": "open-book.ca", "indices": [0, 23]}]}, "description": {"urls": []}}, "protected": false, "followers_count": 26300, "friends_count": 15136, "listed_count": 677, "created_at": "Tue Jul 15 18:43:06 +0000 2008", "favourites_count": 3400, "utc_offset": null, "time_zone": null, "geo_enabled": true, "verified": false, "statuses_count": 6309, "lang": null, "status": {"created_at": "Wed Oct 02 14:49:14 +0000 2019", "id": 1179408000177577989, "id_str": "1179408000177577989", "text": "More great news for the small press community, with so many great independent presses rep'd on the #GGBooks shortli\u2026 https://t.co/C9rCDAzS5x", "truncated": true, "entities": {"hashtags": [{"text": "GGBooks", "indices": [99, 107]}], "symbols": [], "user_mentions": [], "urls": [{"url": "https://t.co/C9rCDAzS5x", "expanded_url": "https://twitter.com/i/web/status/1179408000177577989", "display_url": "twitter.com/i/web/status/1\u2026", "indices": [117, 140]}]}, "source": "<a href=\"https://mobile.twitter.com\" rel=\"nofollow\">Twitter Web App</a>", "in_reply_to_status_id": null, "in_reply_to_status_id_str": null, "in_reply_to_user_id": null, "in_reply_to_user_id_str": null, "in_reply_to_screen_name": null, "geo": null, "coordinates": null, "place": null, "contributors": null, "is_quote_status": false, "retweet_count": 0, "favorite_count": 1, "favorited": false, "retweeted": false, "possibly_sensitive": false, "lang": "en"}, "contributors_enabled": false, "is_translator": false, "is_translation_enabled": false, "profile_background_color": "709397", "profile_background_image_url": "http://abs.twimg.com/images/themes/theme6/bg.gif", "profile_background_image_url_https": "https://abs.twimg.com/images/themes/theme6/bg.gif", "profile_background_tile": false, "profile_image_url": "http://pbs.twimg.com/profile_images/780511322362576896/JZOai6ZK_normal.jpg", "profile_image_url_https": "https://pbs.twimg.com/profile_images/780511322362576896/JZOai6ZK_normal.jpg", "profile_banner_url": "https://pbs.twimg.com/profile_banners/15444168/1428607805", "profile_link_color": "FF3300", "profile_sidebar_border_color": "86A4A6", "profile_sidebar_fill_color": "A0C5C7", "profile_text_color": "333333", "profile_use_background_image": true, "has_extended_profile": false, "default_profile": false, "default_profile_image": false, "following": true, "live_following": false, "follow_request_sent": false, "notifications": false, "muting": false, "blocking": false, "blocked_by": false, "translator_type": "none"}, {"id": 17163113, "id_str": "17163113", "name": "Bal Sieber", "screen_name": "balsieber", "location": "Los Angeles, CA", "description": "\ud83d\udee9 Traveler / \ud83d\udcbbentrepreneur / \ud83d\udd11minimalist https://t.co/DHpleXklcH LAX // SFO // VAN // CDMX", "url": "https://t.co/12Ua21U9oS", "entities": {"url": {"urls": [{"url": "https://t.co/12Ua21U9oS", "expanded_url": "https://www.modernnerd.co", "display_url": "modernnerd.co", "indices": [0, 23]}]}, "description": {"urls": [{"url": "https://t.co/DHpleXklcH", "expanded_url": "http://youtube.com/c/ModernNerd", "display_url": "youtube.com/c/ModernNerd", "indices": [41, 64]}]}}, "protected": false, "followers_count": 2485, "friends_count": 223, "listed_count": 125, "created_at": "Tue Nov 04 18:09:59 +0000 2008", "favourites_count": 1938, "utc_offset": null, "time_zone": null, "geo_enabled": true, "verified": false, "statuses_count": 6246, "lang": null, "status": {"created_at": "Sat May 25 19:09:00 +0000 2019", "id": 1132362950843539457, "id_str": "1132362950843539457", "text": "I\u2019ve got a lot of work to do on myself.\n\nThe shortlist:\n \u2022 Build the body of a primal warrior \ud83c\udff9\n \u2022 Create a mind &amp;\u2026 https://t.co/kyTDEDcxoL", "truncated": true, "entities": {"hashtags": [], "symbols": [], "user_mentions": [], "urls": [{"url": "https://t.co/kyTDEDcxoL", "expanded_url": "https://twitter.com/i/web/status/1132362950843539457", "display_url": "twitter.com/i/web/status/1\u2026", "indices": [120, 143]}]}, "source": "<a href=\"http://instagram.com\" rel=\"nofollow\">Instagram</a>", "in_reply_to_status_id": null, "in_reply_to_status_id_str": null, "in_reply_to_user_id": null, "in_reply_to_user_id_str": null, "in_reply_to_screen_name": null, "geo": {"type": "Point", "coordinates": [34.12858414, -116.03739259]}, "coordinates": {"type": "Point", "coordinates": [-116.03739259, 34.12858414]}, "place": {"id": "41248dbf2870ea3d", "url": "https://api.twitter.com/1.1/geo/id/41248dbf2870ea3d.json", "place_type": "city", "name": "Twentynine Palms", "full_name": "Twentynine Palms, CA", "country_code": "US", "country": "United States", "contained_within": [], "bounding_box": {"type": "Polygon", "coordinates": [[[-116.159527, 34.111434], [-116.0190127, 34.111434], [-116.0190127, 34.157002], [-116.159527, 34.157002]]]}, "attributes": {}}, "contributors": null, "is_quote_status": false, "retweet_count": 0, "favorite_count": 1, "favorited": false, "retweeted": false, "possibly_sensitive": false, "lang": "en"}, "contributors_enabled": false, "is_translator": false, "is_translation_enabled": false, "profile_background_color": "000000", "profile_background_image_url": "http://abs.twimg.com/images/themes/theme1/bg.png", "profile_background_image_url_https": "https://abs.twimg.com/images/themes/theme1/bg.png", "profile_background_tile": false, "profile_image_url": "http://pbs.twimg.com/profile_images/951888020797452288/Lm-hyWpV_normal.jpg", "profile_image_url_https": "https://pbs.twimg.com/profile_images/951888020797452288/Lm-hyWpV_normal.jpg", "profile_banner_url": "https://pbs.twimg.com/profile_banners/17163113/1512761609", "profile_link_color": "E44424", "profile_sidebar_border_color": "000000", "profile_sidebar_fill_color": "FFFFFF", "profile_text_color": "333333", "profile_use_background_image": false, "has_extended_profile": true, "default_profile": false, "default_profile_image": false, "following": true, "live_following": false, "follow_request_sent": false, "notifications": false, "muting": false, "blocking": false, "blocked_by": false, "translator_type": "none"}, {"id": 740109097, "id_str": "740109097", "name": "SarcasticRover", "screen_name": "SarcasticRover", "location": "4th Rock From the Sun", "description": "Doing a science on the red planet. Not @MarsCuriosity. Portrait by @badportraits. Written by @jfiliatrault.", "url": null, "entities": {"description": {"urls": []}}, "protected": false, "followers_count": 963504, "friends_count": 1790, "listed_count": 3630, "created_at": "Mon Aug 06 07:58:05 +0000 2012", "favourites_count": 2698, "utc_offset": null, "time_zone": null, "geo_enabled": true, "verified": false, "statuses_count": 9932, "lang": null, "status": {"created_at": "Thu Aug 29 20:54:31 +0000 2019", "id": 1167178739429494784, "id_str": "1167178739429494784", "text": "I\u2019ll never stop being amazed at humanity\u2019s inherent ability to reach the most amazing heights and explore new front\u2026 https://t.co/DEBt65Cipv", "truncated": true, "entities": {"hashtags": [], "symbols": [], "user_mentions": [], "urls": [{"url": "https://t.co/DEBt65Cipv", "expanded_url": "https://twitter.com/i/web/status/1167178739429494784", "display_url": "twitter.com/i/web/status/1\u2026", "indices": [117, 140]}]}, "source": "<a href=\"https://about.twitter.com/products/tweetdeck\" rel=\"nofollow\">TweetDeck</a>", "in_reply_to_status_id": null, "in_reply_to_status_id_str": null, "in_reply_to_user_id": null, "in_reply_to_user_id_str": null, "in_reply_to_screen_name": null, "geo": null, "coordinates": null, "place": null, "contributors": null, "is_quote_status": true, "quoted_status_id": 1167177722075996165, "quoted_status_id_str": "1167177722075996165", "retweet_count": 74, "favorite_count": 426, "favorited": false, "retweeted": false, "possibly_sensitive": false, "lang": "en"}, "contributors_enabled": false, "is_translator": false, "is_translation_enabled": false, "profile_background_color": "0099B9", "profile_background_image_url": "http://abs.twimg.com/images/themes/theme4/bg.gif", "profile_background_image_url_https": "https://abs.twimg.com/images/themes/theme4/bg.gif", "profile_background_tile": false, "profile_image_url": "http://pbs.twimg.com/profile_images/839728901165203456/mFZ-sZXQ_normal.jpg", "profile_image_url_https": "https://pbs.twimg.com/profile_images/839728901165203456/mFZ-sZXQ_normal.jpg", "profile_banner_url": "https://pbs.twimg.com/profile_banners/740109097/1456842622", "profile_link_color": "0099B9", "profile_sidebar_border_color": "5ED4DC", "profile_sidebar_fill_color": "95E8EC", "profile_text_color": "3C3940", "profile_use_background_image": true, "has_extended_profile": false, "default_profile": false, "default_profile_image": false, "following": true, "live_following": false, "follow_request_sent": false, "notifications": false, "muting": false, "blocking": false, "blocked_by": false, "translator_type": "none"}, {"id": 70345946, "id_str": "70345946", "name": "Dan Abramov (on a vacation)", "screen_name": "dan_abramov", "location": "", "description": "", "url": "https://t.co/W27BzAGyLJ", "entities": {"url": {"urls": [{"url": "https://t.co/W27BzAGyLJ", "expanded_url": "http://overreacted.io", "display_url": "overreacted.io", "indices": [0, 23]}]}, "description": {"urls": []}}, "protected": false, "followers_count": 213655, "friends_count": 942, "listed_count": 3800, "created_at": "Mon Aug 31 08:28:07 +0000 2009", "favourites_count": 59736, "utc_offset": null, "time_zone": null, "geo_enabled": true, "verified": false, "statuses_count": 66902, "lang": null, "status": {"created_at": "Wed Oct 02 14:20:36 +0000 2019", "id": 1179400796993200128, "id_str": "1179400796993200128", "text": "@ryanflorence \ud83e\udd2a", "truncated": false, "entities": {"hashtags": [], "symbols": [], "user_mentions": [{"screen_name": "ryanflorence", "name": "Ryan Florence", "id": 16468446, "id_str": "16468446", "indices": [0, 13]}], "urls": []}, "source": "<a href=\"https://mobile.twitter.com\" rel=\"nofollow\">Twitter Web App</a>", "in_reply_to_status_id": 1179400678910971905, "in_reply_to_status_id_str": "1179400678910971905", "in_reply_to_user_id": 16468446, "in_reply_to_user_id_str": "16468446", "in_reply_to_screen_name": "ryanflorence", "geo": null, "coordinates": null, "place": null, "contributors": null, "is_quote_status": false, "retweet_count": 0, "favorite_count": 5, "favorited": false, "retweeted": false, "lang": "und"}, "contributors_enabled": false, "is_translator": false, "is_translation_enabled": false, "profile_background_color": "000000", "profile_background_image_url": "http://abs.twimg.com/images/themes/theme1/bg.png", "profile_background_image_url_https": "https://abs.twimg.com/images/themes/theme1/bg.png", "profile_background_tile": false, "profile_image_url": "http://pbs.twimg.com/profile_images/1166344766210150401/amRnWzl-_normal.jpg", "profile_image_url_https": "https://pbs.twimg.com/profile_images/1166344766210150401/amRnWzl-_normal.jpg", "profile_link_color": "F58EA8", "profile_sidebar_border_color": "000000", "profile_sidebar_fill_color": "000000", "profile_text_color": "000000", "profile_use_background_image": false, "has_extended_profile": false, "default_profile": false, "default_profile_image": false, "following": true, "live_following": false, "follow_request_sent": false, "notifications": false, "muting": false, "blocking": false, "blocked_by": false, "translator_type": "none"}, {"id": 2845330473, "id_str": "2845330473", "name": "the hog that got away \ud83c\udf33", "screen_name": "halvves", "location": "The World Wide Web", "description": "makes art/trash on the internet, but loves plants more than computers. currently on the @playcanvas team w/ @snap\ud83d\udc7b. ex @magicleap. music @body_origami. he/him", "url": "https://t.co/OiIPUUThq3", "entities": {"url": {"urls": [{"url": "https://t.co/OiIPUUThq3", "expanded_url": "http://halvves.com", "display_url": "halvves.com", "indices": [0, 23]}]}, "description": {"urls": []}}, "protected": false, "followers_count": 478, "friends_count": 584, "listed_count": 10, "created_at": "Sun Oct 26 16:01:02 +0000 2014", "favourites_count": 18353, "utc_offset": null, "time_zone": null, "geo_enabled": false, "verified": false, "statuses_count": 2180, "lang": null, "status": {"created_at": "Tue Oct 01 21:24:39 +0000 2019", "id": 1179145125240266752, "id_str": "1179145125240266752", "text": "RT @mrmaxm: Interior Illumination demo. Realtime direct light with *trick* GI and IBL.\n\nhttps://t.co/LuQXfuY68K\n\n#WebGL #graphics #gamedev\u2026", "truncated": false, "entities": {"hashtags": [{"text": "WebGL", "indices": [113, 119]}, {"text": "graphics", "indices": [120, 129]}, {"text": "gamedev", "indices": [130, 138]}], "symbols": [], "user_mentions": [{"screen_name": "mrmaxm", "name": "Max M", "id": 430752164, "id_str": "430752164", "indices": [3, 10]}], "urls": [{"url": "https://t.co/LuQXfuY68K", "expanded_url": "https://playcanv.as/p/ZV4PW6wr/", "display_url": "playcanv.as/p/ZV4PW6wr/", "indices": [88, 111]}]}, "source": "<a href=\"https://mobile.twitter.com\" rel=\"nofollow\">Twitter Web App</a>", "in_reply_to_status_id": null, "in_reply_to_status_id_str": null, "in_reply_to_user_id": null, "in_reply_to_user_id_str": null, "in_reply_to_screen_name": null, "geo": null, "coordinates": null, "place": null, "contributors": null, "retweeted_status": {"created_at": "Tue Oct 01 20:05:50 +0000 2019", "id": 1179125288099295232, "id_str": "1179125288099295232", "text": "Interior Illumination demo. Realtime direct light with *trick* GI and IBL.\n\nhttps://t.co/LuQXfuY68K\n\n#WebGL\u2026 https://t.co/siz4HxGkOs", "truncated": true, "entities": {"hashtags": [{"text": "WebGL", "indices": [101, 107]}], "symbols": [], "user_mentions": [], "urls": [{"url": "https://t.co/LuQXfuY68K", "expanded_url": "https://playcanv.as/p/ZV4PW6wr/", "display_url": "playcanv.as/p/ZV4PW6wr/", "indices": [76, 99]}, {"url": "https://t.co/siz4HxGkOs", "expanded_url": "https://twitter.com/i/web/status/1179125288099295232", "display_url": "twitter.com/i/web/status/1\u2026", "indices": [109, 132]}]}, "source": "<a href=\"https://mobile.twitter.com\" rel=\"nofollow\">Twitter Web App</a>", "in_reply_to_status_id": null, "in_reply_to_status_id_str": null, "in_reply_to_user_id": null, "in_reply_to_user_id_str": null, "in_reply_to_screen_name": null, "geo": null, "coordinates": null, "place": null, "contributors": null, "is_quote_status": false, "retweet_count": 26, "favorite_count": 107, "favorited": false, "retweeted": false, "possibly_sensitive": false, "lang": "en"}, "is_quote_status": false, "retweet_count": 26, "favorite_count": 0, "favorited": false, "retweeted": false, "possibly_sensitive": false, "lang": "en"}, "contributors_enabled": false, "is_translator": false, "is_translation_enabled": false, "profile_background_color": "000000", "profile_background_image_url": "http://abs.twimg.com/images/themes/theme1/bg.png", "profile_background_image_url_https": "https://abs.twimg.com/images/themes/theme1/bg.png", "profile_background_tile": false, "profile_image_url": "http://pbs.twimg.com/profile_images/1158837593225621504/CFvprcdM_normal.jpg", "profile_image_url_https": "https://pbs.twimg.com/profile_images/1158837593225621504/CFvprcdM_normal.jpg", "profile_banner_url": "https://pbs.twimg.com/profile_banners/2845330473/1562024351", "profile_link_color": "0000FF", "profile_sidebar_border_color": "000000", "profile_sidebar_fill_color": "000000", "profile_text_color": "000000", "profile_use_background_image": false, "has_extended_profile": false, "default_profile": false, "default_profile_image": false, "following": true, "live_following": false, "follow_request_sent": false, "notifications": false, "muting": false, "blocking": false, "blocked_by": false, "translator_type": "none"}, {"id": 15571887, "id_str": "15571887", "name": "Anna Powell-Smith", "screen_name": "darkgreener", "location": "Stroud/London, UK", "description": "Code, data, wealth, land. Running https://t.co/l546Rmohwq. Chief product officer @f_l_o_u_r_i_s_h. Also https://t.co/0JWfxEVIE9 https://t.co/fstuTS6hjB. Advisor @TaxJusticeUK.", "url": "https://t.co/pcdvBeoWgz", "entities": {"url": {"urls": [{"url": "https://t.co/pcdvBeoWgz", "expanded_url": "http://anna.ps", "display_url": "anna.ps", "indices": [0, 23]}]}, "description": {"urls": [{"url": "https://t.co/l546Rmohwq", "expanded_url": "http://missingnumbers.org", "display_url": "missingnumbers.org", "indices": [34, 57]}, {"url": "https://t.co/0JWfxEVIE9", "expanded_url": "http://ebmdatalab.net", "display_url": "ebmdatalab.net", "indices": [104, 127]}, {"url": "https://t.co/fstuTS6hjB", "expanded_url": "http://whoownsengland.org", "display_url": "whoownsengland.org", "indices": [128, 151]}]}}, "protected": false, "followers_count": 7712, "friends_count": 924, "listed_count": 352, "created_at": "Wed Jul 23 20:47:20 +0000 2008", "favourites_count": 1730, "utc_offset": null, "time_zone": null, "geo_enabled": true, "verified": false, "statuses_count": 1559, "lang": null, "status": {"created_at": "Tue Oct 01 23:49:43 +0000 2019", "id": 1179181631921360896, "id_str": "1179181631921360896", "text": "@tmcw My solution to this problem is https://t.co/cCzH2dWcQv + wget for the audio files + offline Spotify playlist", "truncated": false, "entities": {"hashtags": [], "symbols": [], "user_mentions": [{"screen_name": "tmcw", "name": "Tom MacWright", "id": 1458271, "id_str": "1458271", "indices": [0, 5]}], "urls": [{"url": "https://t.co/cCzH2dWcQv", "expanded_url": "https://mbctapp.oxfordmindfulness.org/", "display_url": "mbctapp.oxfordmindfulness.org", "indices": [37, 60]}]}, "source": "<a href=\"https://mobile.twitter.com\" rel=\"nofollow\">Twitter Web App</a>", "in_reply_to_status_id": 1179180297453096960, "in_reply_to_status_id_str": "1179180297453096960", "in_reply_to_user_id": 1458271, "in_reply_to_user_id_str": "1458271", "in_reply_to_screen_name": "tmcw", "geo": null, "coordinates": null, "place": null, "contributors": null, "is_quote_status": false, "retweet_count": 0, "favorite_count": 0, "favorited": false, "retweeted": false, "possibly_sensitive": false, "lang": "en"}, "contributors_enabled": false, "is_translator": false, "is_translation_enabled": false, "profile_background_color": "C0DEED", "profile_background_image_url": "http://abs.twimg.com/images/themes/theme1/bg.png", "profile_background_image_url_https": "https://abs.twimg.com/images/themes/theme1/bg.png", "profile_background_tile": false, "profile_image_url": "http://pbs.twimg.com/profile_images/1112823501537333248/usv1OcOH_normal.png", "profile_image_url_https": "https://pbs.twimg.com/profile_images/1112823501537333248/usv1OcOH_normal.png", "profile_link_color": "1DA1F2", "profile_sidebar_border_color": "C0DEED", "profile_sidebar_fill_color": "DDEEF6", "profile_text_color": "333333", "profile_use_background_image": true, "has_extended_profile": false, "default_profile": true, "default_profile_image": false, "following": true, "live_following": false, "follow_request_sent": false, "notifications": false, "muting": false, "blocking": false, "blocked_by": false, "translator_type": "none"}, {"id": 583550026, "id_str": "583550026", "name": "markusT", "screen_name": "markusT_inkfood", "location": "", "description": "Working on games every day. Code, draw,play & blog about gamedev on https://t.co/OTvTCtZWOx", "url": "http://t.co/nAuUGeuXL7", "entities": {"url": {"urls": [{"url": "http://t.co/nAuUGeuXL7", "expanded_url": "http://inkfood.com", "display_url": "inkfood.com", "indices": [0, 22]}]}, "description": {"urls": [{"url": "https://t.co/OTvTCtZWOx", "expanded_url": "http://inkfood.com", "display_url": "inkfood.com", "indices": [68, 91]}]}}, "protected": false, "followers_count": 67, "friends_count": 197, "listed_count": 0, "created_at": "Fri May 18 07:00:09 +0000 2012", "favourites_count": 301, "utc_offset": null, "time_zone": null, "geo_enabled": false, "verified": false, "statuses_count": 214, "lang": null, "status": {"created_at": "Mon Jul 08 17:58:14 +0000 2019", "id": 1148290206136766466, "id_str": "1148290206136766466", "text": "Bounciest bushes ever :o. Testing custom spring physics in 3d and having a lot of fun with it. \n #gamedev #lowpoly\u2026 https://t.co/Pngk8PVNPK", "truncated": true, "entities": {"hashtags": [{"text": "gamedev", "indices": [97, 105]}, {"text": "lowpoly", "indices": [106, 114]}], "symbols": [], "user_mentions": [], "urls": [{"url": "https://t.co/Pngk8PVNPK", "expanded_url": "https://twitter.com/i/web/status/1148290206136766466", "display_url": "twitter.com/i/web/status/1\u2026", "indices": [116, 139]}]}, "source": "<a href=\"http://twitter.com\" rel=\"nofollow\">Twitter Web Client</a>", "in_reply_to_status_id": null, "in_reply_to_status_id_str": null, "in_reply_to_user_id": null, "in_reply_to_user_id_str": null, "in_reply_to_screen_name": null, "geo": null, "coordinates": null, "place": null, "contributors": null, "is_quote_status": false, "retweet_count": 2, "favorite_count": 3, "favorited": false, "retweeted": false, "possibly_sensitive": false, "lang": "en"}, "contributors_enabled": false, "is_translator": false, "is_translation_enabled": true, "profile_background_color": "C0DEED", "profile_background_image_url": "http://abs.twimg.com/images/themes/theme1/bg.png", "profile_background_image_url_https": "https://abs.twimg.com/images/themes/theme1/bg.png", "profile_background_tile": false, "profile_image_url": "http://pbs.twimg.com/profile_images/596364500325928961/6bf7MZdc_normal.png", "profile_image_url_https": "https://pbs.twimg.com/profile_images/596364500325928961/6bf7MZdc_normal.png", "profile_banner_url": "https://pbs.twimg.com/profile_banners/583550026/1405758215", "profile_link_color": "1DA1F2", "profile_sidebar_border_color": "C0DEED", "profile_sidebar_fill_color": "DDEEF6", "profile_text_color": "333333", "profile_use_background_image": true, "has_extended_profile": false, "default_profile": true, "default_profile_image": false, "following": true, "live_following": false, "follow_request_sent": false, "notifications": false, "muting": false, "blocking": false, "blocked_by": false, "translator_type": "none"}, {"id": 252761153, "id_str": "252761153", "name": "Susie Lu", "screen_name": "DataToViz", "location": "", "description": "Senior Data Visualization Engineer at Netflix. Art at  https://t.co/Hucx8cpSNP", "url": "https://t.co/ayPyNRz6dh", "entities": {"url": {"urls": [{"url": "https://t.co/ayPyNRz6dh", "expanded_url": "https://susielu.com", "display_url": "susielu.com", "indices": [0, 23]}]}, "description": {"urls": [{"url": "https://t.co/Hucx8cpSNP", "expanded_url": "http://instagram.com/susie_draws", "display_url": "instagram.com/susie_draws", "indices": [55, 78]}]}}, "protected": false, "followers_count": 12484, "friends_count": 239, "listed_count": 496, "created_at": "Tue Feb 15 21:18:15 +0000 2011", "favourites_count": 3008, "utc_offset": null, "time_zone": null, "geo_enabled": false, "verified": false, "statuses_count": 1111, "lang": null, "status": {"created_at": "Thu Sep 05 20:20:45 +0000 2019", "id": 1169706956161839104, "id_str": "1169706956161839104", "text": "RT @veltman: TIL about the book The Algorithmic Beauty of Plants, which is so nerdy in the best way https://t.co/ceWYXdTjjE https://t.co/IG\u2026", "truncated": false, "entities": {"hashtags": [], "symbols": [], "user_mentions": [{"screen_name": "veltman", "name": "Noah Veltman", "id": 17673012, "id_str": "17673012", "indices": [3, 11]}], "urls": [{"url": "https://t.co/ceWYXdTjjE", "expanded_url": "http://algorithmicbotany.org/papers/#abop", "display_url": "algorithmicbotany.org/papers/#abop", "indices": [100, 123]}]}, "source": "<a href=\"http://twitter.com/download/android\" rel=\"nofollow\">Twitter for Android</a>", "in_reply_to_status_id": null, "in_reply_to_status_id_str": null, "in_reply_to_user_id": null, "in_reply_to_user_id_str": null, "in_reply_to_screen_name": null, "geo": null, "coordinates": null, "place": null, "contributors": null, "retweeted_status": {"created_at": "Thu Sep 05 17:40:49 +0000 2019", "id": 1169666708103032832, "id_str": "1169666708103032832", "text": "TIL about the book The Algorithmic Beauty of Plants, which is so nerdy in the best way https://t.co/ceWYXdTjjE https://t.co/IGLsZNEmut", "truncated": false, "entities": {"hashtags": [], "symbols": [], "user_mentions": [], "urls": [{"url": "https://t.co/ceWYXdTjjE", "expanded_url": "http://algorithmicbotany.org/papers/#abop", "display_url": "algorithmicbotany.org/papers/#abop", "indices": [87, 110]}], "media": [{"id": 1169666704382709766, "id_str": "1169666704382709766", "indices": [111, 134], "media_url": "http://pbs.twimg.com/media/EDt9q6RVUAYgpCG.png", "media_url_https": "https://pbs.twimg.com/media/EDt9q6RVUAYgpCG.png", "url": "https://t.co/IGLsZNEmut", "display_url": "pic.twitter.com/IGLsZNEmut", "expanded_url": "https://twitter.com/veltman/status/1169666708103032832/photo/1", "type": "photo", "sizes": {"medium": {"w": 510, "h": 715, "resize": "fit"}, "large": {"w": 510, "h": 715, "resize": "fit"}, "thumb": {"w": 150, "h": 150, "resize": "crop"}, "small": {"w": 485, "h": 680, "resize": "fit"}}}]}, "extended_entities": {"media": [{"id": 1169666704382709766, "id_str": "1169666704382709766", "indices": [111, 134], "media_url": "http://pbs.twimg.com/media/EDt9q6RVUAYgpCG.png", "media_url_https": "https://pbs.twimg.com/media/EDt9q6RVUAYgpCG.png", "url": "https://t.co/IGLsZNEmut", "display_url": "pic.twitter.com/IGLsZNEmut", "expanded_url": "https://twitter.com/veltman/status/1169666708103032832/photo/1", "type": "photo", "sizes": {"medium": {"w": 510, "h": 715, "resize": "fit"}, "large": {"w": 510, "h": 715, "resize": "fit"}, "thumb": {"w": 150, "h": 150, "resize": "crop"}, "small": {"w": 485, "h": 680, "resize": "fit"}}}, {"id": 1169666704382689280, "id_str": "1169666704382689280", "indices": [111, 134], "media_url": "http://pbs.twimg.com/media/EDt9q6RVAAAirv5.png", "media_url_https": "https://pbs.twimg.com/media/EDt9q6RVAAAirv5.png", "url": "https://t.co/IGLsZNEmut", "display_url": "pic.twitter.com/IGLsZNEmut", "expanded_url": "https://twitter.com/veltman/status/1169666708103032832/photo/1", "type": "photo", "sizes": {"medium": {"w": 538, "h": 549, "resize": "fit"}, "large": {"w": 538, "h": 549, "resize": "fit"}, "small": {"w": 538, "h": 549, "resize": "fit"}, "thumb": {"w": 150, "h": 150, "resize": "crop"}}}, {"id": 1169666704386875394, "id_str": "1169666704386875394", "indices": [111, 134], "media_url": "http://pbs.twimg.com/media/EDt9q6SU4AI4qZt.png", "media_url_https": "https://pbs.twimg.com/media/EDt9q6SU4AI4qZt.png", "url": "https://t.co/IGLsZNEmut", "display_url": "pic.twitter.com/IGLsZNEmut", "expanded_url": "https://twitter.com/veltman/status/1169666708103032832/photo/1", "type": "photo", "sizes": {"large": {"w": 527, "h": 817, "resize": "fit"}, "medium": {"w": 527, "h": 817, "resize": "fit"}, "thumb": {"w": 150, "h": 150, "resize": "crop"}, "small": {"w": 439, "h": 680, "resize": "fit"}}}]}, "source": "<a href=\"https://mobile.twitter.com\" rel=\"nofollow\">Twitter Web App</a>", "in_reply_to_status_id": null, "in_reply_to_status_id_str": null, "in_reply_to_user_id": null, "in_reply_to_user_id_str": null, "in_reply_to_screen_name": null, "geo": null, "coordinates": null, "place": null, "contributors": null, "is_quote_status": false, "retweet_count": 178, "favorite_count": 587, "favorited": false, "retweeted": false, "possibly_sensitive": false, "lang": "en"}, "is_quote_status": false, "retweet_count": 178, "favorite_count": 0, "favorited": false, "retweeted": false, "possibly_sensitive": false, "lang": "en"}, "contributors_enabled": false, "is_translator": false, "is_translation_enabled": false, "profile_background_color": "323E47", "profile_background_image_url": "http://abs.twimg.com/images/themes/theme17/bg.gif", "profile_background_image_url_https": "https://abs.twimg.com/images/themes/theme17/bg.gif", "profile_background_tile": false, "profile_image_url": "http://pbs.twimg.com/profile_images/848621981482098688/1a7fh28O_normal.jpg", "profile_image_url_https": "https://pbs.twimg.com/profile_images/848621981482098688/1a7fh28O_normal.jpg", "profile_banner_url": "https://pbs.twimg.com/profile_banners/252761153/1488396657", "profile_link_color": "1ACDCF", "profile_sidebar_border_color": "FFFFFF", "profile_sidebar_fill_color": "E6F6F9", "profile_text_color": "333333", "profile_use_background_image": false, "has_extended_profile": false, "default_profile": false, "default_profile_image": false, "following": true, "live_following": false, "follow_request_sent": false, "notifications": false, "muting": false, "blocking": false, "blocked_by": false, "translator_type": "none"}, {"id": 798702708, "id_str": "798702708", "name": "Cosmic Muffin\ud83c\udf3f", "screen_name": "dzifyr", "location": "Lille", "description": "Art director, game artist & illustrator. Part of @klondk! I made a game called Sacramento (https://t.co/kBtjCzYwdf) (she/her)", "url": "https://t.co/hjGCG8EvhT", "entities": {"url": {"urls": [{"url": "https://t.co/hjGCG8EvhT", "expanded_url": "http://www.dziff.com", "display_url": "dziff.com", "indices": [0, 23]}]}, "description": {"urls": [{"url": "https://t.co/kBtjCzYwdf", "expanded_url": "http://dziff.itch.io", "display_url": "dziff.itch.io", "indices": [91, 114]}]}}, "protected": false, "followers_count": 5018, "friends_count": 828, "listed_count": 150, "created_at": "Sun Sep 02 17:31:24 +0000 2012", "favourites_count": 15013, "utc_offset": null, "time_zone": null, "geo_enabled": false, "verified": false, "statuses_count": 3140, "lang": null, "status": {"created_at": "Wed Sep 25 08:13:48 +0000 2019", "id": 1176771772995264513, "id_str": "1176771772995264513", "text": "RT @__lazlo: games that wouldn\u2019t exist if devs were paid by play time:\n\ngoose game\njourney\nflorence\nedith finch\ninside\nfirewatch\ndonut coun\u2026", "truncated": false, "entities": {"hashtags": [], "symbols": [], "user_mentions": [{"screen_name": "__lazlo", "name": "Lazlo", "id": 146953683, "id_str": "146953683", "indices": [3, 11]}], "urls": []}, "source": "<a href=\"https://mobile.twitter.com\" rel=\"nofollow\">Twitter Web App</a>", "in_reply_to_status_id": null, "in_reply_to_status_id_str": null, "in_reply_to_user_id": null, "in_reply_to_user_id_str": null, "in_reply_to_screen_name": null, "geo": null, "coordinates": null, "place": null, "contributors": null, "retweeted_status": {"created_at": "Tue Sep 24 01:44:28 +0000 2019", "id": 1176311405135446017, "id_str": "1176311405135446017", "text": "games that wouldn\u2019t exist if devs were paid by play time:\n\ngoose game\njourney\nflorence\nedith finch\ninside\nfirewatch\u2026 https://t.co/xW8onje0AJ", "truncated": true, "entities": {"hashtags": [], "symbols": [], "user_mentions": [], "urls": [{"url": "https://t.co/xW8onje0AJ", "expanded_url": "https://twitter.com/i/web/status/1176311405135446017", "display_url": "twitter.com/i/web/status/1\u2026", "indices": [117, 140]}]}, "source": "<a href=\"http://twitter.com/download/iphone\" rel=\"nofollow\">Twitter for iPhone</a>", "in_reply_to_status_id": null, "in_reply_to_status_id_str": null, "in_reply_to_user_id": null, "in_reply_to_user_id_str": null, "in_reply_to_screen_name": null, "geo": null, "coordinates": null, "place": null, "contributors": null, "is_quote_status": false, "retweet_count": 4232, "favorite_count": 19660, "favorited": false, "retweeted": false, "lang": "en"}, "is_quote_status": false, "retweet_count": 4232, "favorite_count": 0, "favorited": false, "retweeted": false, "lang": "en"}, "contributors_enabled": false, "is_translator": false, "is_translation_enabled": false, "profile_background_color": "642D8B", "profile_background_image_url": "http://abs.twimg.com/images/themes/theme10/bg.gif", "profile_background_image_url_https": "https://abs.twimg.com/images/themes/theme10/bg.gif", "profile_background_tile": false, "profile_image_url": "http://pbs.twimg.com/profile_images/983818426190848001/_u5cyriO_normal.jpg", "profile_image_url_https": "https://pbs.twimg.com/profile_images/983818426190848001/_u5cyriO_normal.jpg", "profile_banner_url": "https://pbs.twimg.com/profile_banners/798702708/1447690365", "profile_link_color": "FF5900", "profile_sidebar_border_color": "FFFFFF", "profile_sidebar_fill_color": "7AC3EE", "profile_text_color": "3D1957", "profile_use_background_image": true, "has_extended_profile": true, "default_profile": false, "default_profile_image": false, "following": true, "live_following": false, "follow_request_sent": false, "notifications": false, "muting": false, "blocking": false, "blocked_by": false, "translator_type": "none"}, {"id": 3388808835, "id_str": "3388808835", "name": "Juliette \ud83d\udc1f\ud83c\udf1e\ud83c\udf8f", "screen_name": "Cy_lindric", "location": "Paris, France", "description": "Juliette Brocal, human swordfish, illustration tiefling \u30fbGobelins animation 2020 \u2022 pp by @camille_leto", "url": "https://t.co/PWIHye0H5F", "entities": {"url": {"urls": [{"url": "https://t.co/PWIHye0H5F", "expanded_url": "http://cy-lindric.tumblr.com", "display_url": "cy-lindric.tumblr.com", "indices": [0, 23]}]}, "description": {"urls": []}}, "protected": false, "followers_count": 28311, "friends_count": 497, "listed_count": 324, "created_at": "Thu Jul 23 09:16:05 +0000 2015", "favourites_count": 5300, "utc_offset": null, "time_zone": null, "geo_enabled": false, "verified": false, "statuses_count": 5089, "lang": null, "status": {"created_at": "Wed Oct 02 14:02:19 +0000 2019", "id": 1179396195615150080, "id_str": "1179396195615150080", "text": "@estreleta_ It\u2019s exactly what happened to me and I blame @Shliten (try it)", "truncated": false, "entities": {"hashtags": [], "symbols": [], "user_mentions": [{"screen_name": "estreleta_", "name": "estreleta \ud83c\udf20", "id": 2205670982, "id_str": "2205670982", "indices": [0, 11]}, {"screen_name": "Shliten", "name": "Agathe Leroux", "id": 459517214, "id_str": "459517214", "indices": [57, 65]}], "urls": []}, "source": "<a href=\"http://twitter.com/#!/download/ipad\" rel=\"nofollow\">Twitter for iPad</a>", "in_reply_to_status_id": 1179392275564109824, "in_reply_to_status_id_str": "1179392275564109824", "in_reply_to_user_id": 2205670982, "in_reply_to_user_id_str": "2205670982", "in_reply_to_screen_name": "estreleta_", "geo": null, "coordinates": null, "place": null, "contributors": null, "is_quote_status": false, "retweet_count": 0, "favorite_count": 2, "favorited": false, "retweeted": false, "lang": "en"}, "contributors_enabled": false, "is_translator": false, "is_translation_enabled": false, "profile_background_color": "000000", "profile_background_image_url": "http://abs.twimg.com/images/themes/theme1/bg.png", "profile_background_image_url_https": "https://abs.twimg.com/images/themes/theme1/bg.png", "profile_background_tile": false, "profile_image_url": "http://pbs.twimg.com/profile_images/1135816943108218880/gMEseoUU_normal.png", "profile_image_url_https": "https://pbs.twimg.com/profile_images/1135816943108218880/gMEseoUU_normal.png", "profile_banner_url": "https://pbs.twimg.com/profile_banners/3388808835/1563783557", "profile_link_color": "7FDBB6", "profile_sidebar_border_color": "000000", "profile_sidebar_fill_color": "000000", "profile_text_color": "000000", "profile_use_background_image": false, "has_extended_profile": true, "default_profile": false, "default_profile_image": false, "following": true, "live_following": false, "follow_request_sent": false, "notifications": false, "muting": false, "blocking": false, "blocked_by": false, "translator_type": "none"}, {"id": 2200293518, "id_str": "2200293518", "name": "Lulu \ud83e\udd8b\ud83c\udf3a", "screen_name": "LucieViatge", "location": "Montr\u00e9al, Qu\u00e9bec", "description": "Art Director/Character Designer at @KOOPMode and part of @klondk!! Vegan \ud83c\udf3a she/her \u264a\u2653\u2653", "url": null, "entities": {"description": {"urls": []}}, "protected": false, "followers_count": 2397, "friends_count": 645, "listed_count": 41, "created_at": "Sun Nov 17 22:27:14 +0000 2013", "favourites_count": 8003, "utc_offset": null, "time_zone": null, "geo_enabled": false, "verified": false, "statuses_count": 1549, "lang": null, "status": {"created_at": "Mon Sep 30 23:28:57 +0000 2019", "id": 1178814017009270785, "id_str": "1178814017009270785", "text": "RT @NoraPotwora: You know guys, I'm dumb and made a huge mistake while ordering prints so here's \ud835\uddd4\ud835\udde5\ud835\udde7 \ud835\udde3\ud835\udde5\ud835\udddc\ud835\udde1\ud835\udde7 \ud835\udde5\ud835\uddd4\ud835\uddd9\ud835\uddd9\ud835\udddf\ud835\uddd8!\n\n\ud835\uddd9\ud835\udde2\ud835\udddf\ud835\udddf\ud835\udde2\ud835\uddea and \ud835\udde5\ud835\uddd8\ud835\udde7\ud835\uddea\ud835\uddd8\ud835\uddd8\ud835\udde7 to e\u2026", "truncated": false, "entities": {"hashtags": [], "symbols": [], "user_mentions": [{"screen_name": "NoraPotwora", "name": "Nora Potwora", "id": 3358628320, "id_str": "3358628320", "indices": [3, 15]}], "urls": []}, "source": "<a href=\"http://twitter.com/download/android\" rel=\"nofollow\">Twitter for Android</a>", "in_reply_to_status_id": null, "in_reply_to_status_id_str": null, "in_reply_to_user_id": null, "in_reply_to_user_id_str": null, "in_reply_to_screen_name": null, "geo": null, "coordinates": null, "place": null, "contributors": null, "retweeted_status": {"created_at": "Mon Sep 30 22:55:19 +0000 2019", "id": 1178805552509603841, "id_str": "1178805552509603841", "text": "You know guys, I'm dumb and made a huge mistake while ordering prints so here's \ud835\uddd4\ud835\udde5\ud835\udde7 \ud835\udde3\ud835\udde5\ud835\udddc\ud835\udde1\ud835\udde7 \ud835\udde5\ud835\uddd4\ud835\uddd9\ud835\uddd9\ud835\udddf\ud835\uddd8!\n\n\ud835\uddd9\ud835\udde2\ud835\udddf\ud835\udddf\ud835\udde2\ud835\uddea and \ud835\udde5\ud835\uddd8\ud835\udde7\ud835\uddea\ud835\uddd8\u2026 https://t.co/rvCao6trgL", "truncated": true, "entities": {"hashtags": [], "symbols": [], "user_mentions": [], "urls": [{"url": "https://t.co/rvCao6trgL", "expanded_url": "https://twitter.com/i/web/status/1178805552509603841", "display_url": "twitter.com/i/web/status/1\u2026", "indices": [117, 140]}]}, "source": "<a href=\"https://mobile.twitter.com\" rel=\"nofollow\">Twitter Web App</a>", "in_reply_to_status_id": null, "in_reply_to_status_id_str": null, "in_reply_to_user_id": null, "in_reply_to_user_id_str": null, "in_reply_to_screen_name": null, "geo": null, "coordinates": null, "place": null, "contributors": null, "is_quote_status": false, "retweet_count": 1076, "favorite_count": 2141, "favorited": false, "retweeted": false, "possibly_sensitive": false, "lang": "en"}, "is_quote_status": false, "retweet_count": 1076, "favorite_count": 0, "favorited": false, "retweeted": false, "lang": "en"}, "contributors_enabled": false, "is_translator": false, "is_translation_enabled": false, "profile_background_color": "345461", "profile_background_image_url": "http://abs.twimg.com/images/themes/theme1/bg.png", "profile_background_image_url_https": "https://abs.twimg.com/images/themes/theme1/bg.png", "profile_background_tile": true, "profile_image_url": "http://pbs.twimg.com/profile_images/1106402328758939648/2AHReTVl_normal.jpg", "profile_image_url_https": "https://pbs.twimg.com/profile_images/1106402328758939648/2AHReTVl_normal.jpg", "profile_banner_url": "https://pbs.twimg.com/profile_banners/2200293518/1457649371", "profile_link_color": "91D2FA", "profile_sidebar_border_color": "FFFFFF", "profile_sidebar_fill_color": "DDEEF6", "profile_text_color": "333333", "profile_use_background_image": true, "has_extended_profile": true, "default_profile": false, "default_profile_image": false, "following": true, "live_following": false, "follow_request_sent": false, "notifications": false, "muting": false, "blocking": false, "blocked_by": false, "translator_type": "none"}, {"id": 18229224, "id_str": "18229224", "name": "William Ngan", "screen_name": "williamngan", "location": "San Francisco", "description": "", "url": "http://t.co/Nci8Zi74HX", "entities": {"url": {"urls": [{"url": "http://t.co/Nci8Zi74HX", "expanded_url": "http://williamngan.com", "display_url": "williamngan.com", "indices": [0, 22]}]}, "description": {"urls": []}}, "protected": false, "followers_count": 1167, "friends_count": 197, "listed_count": 58, "created_at": "Thu Dec 18 23:58:35 +0000 2008", "favourites_count": 1631, "utc_offset": null, "time_zone": null, "geo_enabled": false, "verified": false, "statuses_count": 352, "lang": null, "status": {"created_at": "Thu Sep 26 18:38:22 +0000 2019", "id": 1177291337940365312, "id_str": "1177291337940365312", "text": "RT @mattdesl: I've open sourced the demos &amp; course notes from my recent @shapeofdata \"Intro to Creative Coding\" workshop on p5.js and Tone.\u2026", "truncated": false, "entities": {"hashtags": [], "symbols": [], "user_mentions": [{"screen_name": "mattdesl", "name": "Matt DesLauriers", "id": 492678204, "id_str": "492678204", "indices": [3, 12]}, {"screen_name": "shapeofdata", "name": "ShapeOfData - Code&Design Workshops", "id": 1162381475439947776, "id_str": "1162381475439947776", "indices": [76, 88]}], "urls": []}, "source": "<a href=\"http://twitter.com/download/iphone\" rel=\"nofollow\">Twitter for iPhone</a>", "in_reply_to_status_id": null, "in_reply_to_status_id_str": null, "in_reply_to_user_id": null, "in_reply_to_user_id_str": null, "in_reply_to_screen_name": null, "geo": null, "coordinates": null, "place": null, "contributors": null, "retweeted_status": {"created_at": "Thu Sep 26 08:23:36 +0000 2019", "id": 1177136627455537152, "id_str": "1177136627455537152", "text": "I've open sourced the demos &amp; course notes from my recent @shapeofdata \"Intro to Creative Coding\" workshop on p5.js\u2026 https://t.co/LuBojBGxOk", "truncated": true, "entities": {"hashtags": [], "symbols": [], "user_mentions": [{"screen_name": "shapeofdata", "name": "ShapeOfData - Code&Design Workshops", "id": 1162381475439947776, "id_str": "1162381475439947776", "indices": [62, 74]}], "urls": [{"url": "https://t.co/LuBojBGxOk", "expanded_url": "https://twitter.com/i/web/status/1177136627455537152", "display_url": "twitter.com/i/web/status/1\u2026", "indices": [121, 144]}]}, "source": "<a href=\"https://mobile.twitter.com\" rel=\"nofollow\">Twitter Web App</a>", "in_reply_to_status_id": null, "in_reply_to_status_id_str": null, "in_reply_to_user_id": null, "in_reply_to_user_id_str": null, "in_reply_to_screen_name": null, "geo": null, "coordinates": null, "place": null, "contributors": null, "is_quote_status": false, "retweet_count": 622, "favorite_count": 2711, "favorited": false, "retweeted": false, "possibly_sensitive": false, "lang": "en"}, "is_quote_status": false, "retweet_count": 622, "favorite_count": 0, "favorited": false, "retweeted": false, "lang": "en"}, "contributors_enabled": false, "is_translator": false, "is_translation_enabled": false, "profile_background_color": "FFFFFF", "profile_background_image_url": "http://abs.twimg.com/images/themes/theme1/bg.png", "profile_background_image_url_https": "https://abs.twimg.com/images/themes/theme1/bg.png", "profile_background_tile": true, "profile_image_url": "http://pbs.twimg.com/profile_images/590072655631364096/xEle-ELy_normal.png", "profile_image_url_https": "https://pbs.twimg.com/profile_images/590072655631364096/xEle-ELy_normal.png", "profile_link_color": "757575", "profile_sidebar_border_color": "E0E0E0", "profile_sidebar_fill_color": "FFFFFF", "profile_text_color": "000000", "profile_use_background_image": false, "has_extended_profile": false, "default_profile": false, "default_profile_image": false, "following": true, "live_following": false, "follow_request_sent": false, "notifications": false, "muting": false, "blocking": false, "blocked_by": false, "translator_type": "none"}, {"id": 1163095897, "id_str": "1163095897", "name": "Klondike", "screen_name": "klondk", "location": "Lille, France", "description": "Game collective. Mainly known for doing stuff.", "url": "http://t.co/9Tx6DUXU7W", "entities": {"url": {"urls": [{"url": "http://t.co/9Tx6DUXU7W", "expanded_url": "http://www.klondike.fr", "display_url": "klondike.fr", "indices": [0, 22]}]}, "description": {"urls": []}}, "protected": false, "followers_count": 3663, "friends_count": 10, "listed_count": 92, "created_at": "Sat Feb 09 14:21:59 +0000 2013", "favourites_count": 57, "utc_offset": null, "time_zone": null, "geo_enabled": false, "verified": false, "statuses_count": 1580, "lang": null, "status": {"created_at": "Wed Mar 06 18:01:12 +0000 2019", "id": 1103354860290953217, "id_str": "1103354860290953217", "text": "RT @skeletonbiz: Vignettes is now available on PC/Mac! \ud83d\udcfa\n\nGet the game on Steam~\u260e\ufe0f\nhttps://t.co/4pS0TozhKP\n\nOr get the game on Itch to acce\u2026", "truncated": false, "entities": {"hashtags": [], "symbols": [], "user_mentions": [{"screen_name": "skeletonbiz", "name": "Skeleton Business", "id": 787991585862610945, "id_str": "787991585862610945", "indices": [3, 15]}], "urls": [{"url": "https://t.co/4pS0TozhKP", "expanded_url": "https://store.steampowered.com/app/944340/Vignettes/", "display_url": "store.steampowered.com/app/944340/Vig\u2026", "indices": [83, 106]}]}, "source": "<a href=\"http://twitter.com/download/android\" rel=\"nofollow\">Twitter for Android</a>", "in_reply_to_status_id": null, "in_reply_to_status_id_str": null, "in_reply_to_user_id": null, "in_reply_to_user_id_str": null, "in_reply_to_screen_name": null, "geo": null, "coordinates": null, "place": null, "contributors": null, "retweeted_status": {"created_at": "Wed Mar 06 17:46:20 +0000 2019", "id": 1103351118300626945, "id_str": "1103351118300626945", "text": "Vignettes is now available on PC/Mac! \ud83d\udcfa\n\nGet the game on Steam~\u260e\ufe0f\nhttps://t.co/4pS0TozhKP\n\nOr get the game on Itch\u2026 https://t.co/7VZQ7if3SA", "truncated": true, "entities": {"hashtags": [], "symbols": [], "user_mentions": [], "urls": [{"url": "https://t.co/4pS0TozhKP", "expanded_url": "https://store.steampowered.com/app/944340/Vignettes/", "display_url": "store.steampowered.com/app/944340/Vig\u2026", "indices": [66, 89]}, {"url": "https://t.co/7VZQ7if3SA", "expanded_url": "https://twitter.com/i/web/status/1103351118300626945", "display_url": "twitter.com/i/web/status/1\u2026", "indices": [116, 139]}]}, "source": "<a href=\"http://twitter.com\" rel=\"nofollow\">Twitter Web Client</a>", "in_reply_to_status_id": null, "in_reply_to_status_id_str": null, "in_reply_to_user_id": null, "in_reply_to_user_id_str": null, "in_reply_to_screen_name": null, "geo": null, "coordinates": null, "place": null, "contributors": null, "is_quote_status": false, "retweet_count": 58, "favorite_count": 76, "favorited": false, "retweeted": false, "possibly_sensitive": false, "lang": "en"}, "is_quote_status": false, "retweet_count": 58, "favorite_count": 0, "favorited": false, "retweeted": false, "possibly_sensitive": false, "lang": "en"}, "contributors_enabled": false, "is_translator": false, "is_translation_enabled": false, "profile_background_color": "C0DEED", "profile_background_image_url": "http://abs.twimg.com/images/themes/theme1/bg.png", "profile_background_image_url_https": "https://abs.twimg.com/images/themes/theme1/bg.png", "profile_background_tile": true, "profile_image_url": "http://pbs.twimg.com/profile_images/589865584747216896/bzQK23Db_normal.png", "profile_image_url_https": "https://pbs.twimg.com/profile_images/589865584747216896/bzQK23Db_normal.png", "profile_banner_url": "https://pbs.twimg.com/profile_banners/1163095897/1429469807", "profile_link_color": "FAB81E", "profile_sidebar_border_color": "FFFFFF", "profile_sidebar_fill_color": "DDEEF6", "profile_text_color": "333333", "profile_use_background_image": true, "has_extended_profile": false, "default_profile": false, "default_profile_image": false, "following": true, "live_following": false, "follow_request_sent": false, "notifications": false, "muting": false, "blocking": false, "blocked_by": false, "translator_type": "none"}, {"id": 14277135, "id_str": "14277135", "name": "David McCandless", "screen_name": "mccandelish", "location": "London", "description": "LDN-based writer, designer, author of Information is Beautiful. Posting here for my own reference & memory. Follow @infobeautiful for infographic / dataviz work", "url": "https://t.co/rV4h75saCV", "entities": {"url": {"urls": [{"url": "https://t.co/rV4h75saCV", "expanded_url": "http://www.davidmccandless.com", "display_url": "davidmccandless.com", "indices": [0, 23]}]}, "description": {"urls": []}}, "protected": false, "followers_count": 23395, "friends_count": 55, "listed_count": 1538, "created_at": "Tue Apr 01 18:58:51 +0000 2008", "favourites_count": 280, "utc_offset": null, "time_zone": null, "geo_enabled": false, "verified": false, "statuses_count": 1512, "lang": null, "status": {"created_at": "Mon Sep 09 21:59:07 +0000 2019", "id": 1171181262318555137, "id_str": "1171181262318555137", "text": "RT @tnajournal: @mccandelish Now available in audio, FYI: https://t.co/V2STAEM2vN", "truncated": false, "entities": {"hashtags": [], "symbols": [], "user_mentions": [{"screen_name": "tnajournal", "name": "The New Atlantis", "id": 108369796, "id_str": "108369796", "indices": [3, 14]}, {"screen_name": "mccandelish", "name": "David McCandless", "id": 14277135, "id_str": "14277135", "indices": [16, 28]}], "urls": [{"url": "https://t.co/V2STAEM2vN", "expanded_url": "https://twitter.com/tnajournal/status/1171111024344408064", "display_url": "twitter.com/tnajournal/sta\u2026", "indices": [58, 81]}]}, "source": "<a href=\"https://about.twitter.com/products/tweetdeck\" rel=\"nofollow\">TweetDeck</a>", "in_reply_to_status_id": null, "in_reply_to_status_id_str": null, "in_reply_to_user_id": null, "in_reply_to_user_id_str": null, "in_reply_to_screen_name": null, "geo": null, "coordinates": null, "place": null, "contributors": null, "retweeted_status": {"created_at": "Mon Sep 09 18:07:49 +0000 2019", "id": 1171123053650153477, "id_str": "1171123053650153477", "text": "@mccandelish Now available in audio, FYI: https://t.co/V2STAEM2vN", "truncated": false, "entities": {"hashtags": [], "symbols": [], "user_mentions": [{"screen_name": "mccandelish", "name": "David McCandless", "id": 14277135, "id_str": "14277135", "indices": [0, 12]}], "urls": [{"url": "https://t.co/V2STAEM2vN", "expanded_url": "https://twitter.com/tnajournal/status/1171111024344408064", "display_url": "twitter.com/tnajournal/sta\u2026", "indices": [42, 65]}]}, "source": "<a href=\"https://mobile.twitter.com\" rel=\"nofollow\">Twitter Web App</a>", "in_reply_to_status_id": 931478117763469312, "in_reply_to_status_id_str": "931478117763469312", "in_reply_to_user_id": 14277135, "in_reply_to_user_id_str": "14277135", "in_reply_to_screen_name": "mccandelish", "geo": null, "coordinates": null, "place": null, "contributors": null, "is_quote_status": true, "quoted_status_id": 1171111024344408064, "quoted_status_id_str": "1171111024344408064", "retweet_count": 1, "favorite_count": 0, "favorited": false, "retweeted": false, "possibly_sensitive": false, "lang": "en"}, "is_quote_status": true, "quoted_status_id": 1171111024344408064, "quoted_status_id_str": "1171111024344408064", "retweet_count": 1, "favorite_count": 0, "favorited": false, "retweeted": false, "possibly_sensitive": false, "lang": "en"}, "contributors_enabled": false, "is_translator": false, "is_translation_enabled": false, "profile_background_color": "9AE4E8", "profile_background_image_url": "http://abs.twimg.com/images/themes/theme1/bg.png", "profile_background_image_url_https": "https://abs.twimg.com/images/themes/theme1/bg.png", "profile_background_tile": true, "profile_image_url": "http://pbs.twimg.com/profile_images/83855034/me_avatar2_normal.jpg", "profile_image_url_https": "https://pbs.twimg.com/profile_images/83855034/me_avatar2_normal.jpg", "profile_link_color": "0084B4", "profile_sidebar_border_color": "BDDCAD", "profile_sidebar_fill_color": "DDFFCC", "profile_text_color": "333333", "profile_use_background_image": true, "has_extended_profile": false, "default_profile": false, "default_profile_image": false, "following": true, "live_following": false, "follow_request_sent": false, "notifications": false, "muting": false, "blocking": false, "blocked_by": false, "translator_type": "none"}, {"id": 9942252, "id_str": "9942252", "name": "Stefan Wehrmeyer", "screen_name": "stefanwehrmeyer", "location": "Berlin", "description": "FragDenStaat.de, OKFN.de", "url": "http://t.co/ipozU0NnUe", "entities": {"url": {"urls": [{"url": "http://t.co/ipozU0NnUe", "expanded_url": "http://stefanwehrmeyer.com", "display_url": "stefanwehrmeyer.com", "indices": [0, 22]}]}, "description": {"urls": []}}, "protected": false, "followers_count": 2840, "friends_count": 133, "listed_count": 204, "created_at": "Sun Nov 04 16:32:25 +0000 2007", "favourites_count": 603, "utc_offset": null, "time_zone": null, "geo_enabled": true, "verified": false, "statuses_count": 1063, "lang": null, "status": {"created_at": "Wed Sep 11 18:00:58 +0000 2019", "id": 1171846105518227457, "id_str": "1171846105518227457", "text": "@HalukaMB Es gibt auch einen JSON-Endpoint: https://t.co/hAfVEfAsIA", "truncated": false, "entities": {"hashtags": [], "symbols": [], "user_mentions": [{"screen_name": "HalukaMB", "name": "Haluka Maier-Borst", "id": 460957118, "id_str": "460957118", "indices": [0, 9]}], "urls": [{"url": "https://t.co/hAfVEfAsIA", "expanded_url": "https://iceportal.de/api1/rs/status", "display_url": "iceportal.de/api1/rs/status", "indices": [44, 67]}]}, "source": "<a href=\"https://mobile.twitter.com\" rel=\"nofollow\">Twitter Web App</a>", "in_reply_to_status_id": 1171819960815050752, "in_reply_to_status_id_str": "1171819960815050752", "in_reply_to_user_id": 460957118, "in_reply_to_user_id_str": "460957118", "in_reply_to_screen_name": "HalukaMB", "geo": null, "coordinates": null, "place": null, "contributors": null, "is_quote_status": false, "retweet_count": 0, "favorite_count": 0, "favorited": false, "retweeted": false, "possibly_sensitive": false, "lang": "de"}, "contributors_enabled": false, "is_translator": false, "is_translation_enabled": false, "profile_background_color": "FFFFFF", "profile_background_image_url": "http://abs.twimg.com/images/themes/theme1/bg.png", "profile_background_image_url_https": "https://abs.twimg.com/images/themes/theme1/bg.png", "profile_background_tile": true, "profile_image_url": "http://pbs.twimg.com/profile_images/533974112083775489/vTO_xrZB_normal.jpeg", "profile_image_url_https": "https://pbs.twimg.com/profile_images/533974112083775489/vTO_xrZB_normal.jpeg", "profile_banner_url": "https://pbs.twimg.com/profile_banners/9942252/1416144672", "profile_link_color": "000000", "profile_sidebar_border_color": "FFFFFF", "profile_sidebar_fill_color": "FFFFFF", "profile_text_color": "333333", "profile_use_background_image": true, "has_extended_profile": false, "default_profile": false, "default_profile_image": false, "following": true, "live_following": false, "follow_request_sent": false, "notifications": false, "muting": false, "blocking": false, "blocked_by": false, "translator_type": "none"}, {"id": 921398240, "id_str": "921398240", "name": "egghead.io", "screen_name": "eggheadio", "location": "at the computer", "description": "High quality, concise web development screencasts. Coding with expert open-source contributors.  Let\u2019s make the web better. \u2764\ufe0f    support@egghead.io for help.", "url": "https://t.co/bpeGX9yFJ8", "entities": {"url": {"urls": [{"url": "https://t.co/bpeGX9yFJ8", "expanded_url": "http://egghead.io/podcasts", "display_url": "egghead.io/podcasts", "indices": [0, 23]}]}, "description": {"urls": []}}, "protected": false, "followers_count": 68879, "friends_count": 138, "listed_count": 1547, "created_at": "Fri Nov 02 17:03:39 +0000 2012", "favourites_count": 1183, "utc_offset": null, "time_zone": null, "geo_enabled": false, "verified": false, "statuses_count": 14754, "lang": null, "status": {"created_at": "Wed Oct 02 16:08:00 +0000 2019", "id": 1179427824433848320, "id_str": "1179427824433848320", "text": "Introduction to VSCode and VSCode Insiders - #vscode lesson by @MrAhmadAwais https://t.co/OEaLsz1C1M", "truncated": false, "entities": {"hashtags": [{"text": "vscode", "indices": [45, 52]}], "symbols": [], "user_mentions": [{"screen_name": "MrAhmadAwais", "name": "AWAIS", "id": 216727067, "id_str": "216727067", "indices": [63, 76]}], "urls": [{"url": "https://t.co/OEaLsz1C1M", "expanded_url": "http://bit.ly/2mOdOTa", "display_url": "bit.ly/2mOdOTa", "indices": [77, 100]}]}, "source": "<a href=\"https://buffer.com\" rel=\"nofollow\">Buffer</a>", "in_reply_to_status_id": null, "in_reply_to_status_id_str": null, "in_reply_to_user_id": null, "in_reply_to_user_id_str": null, "in_reply_to_screen_name": null, "geo": null, "coordinates": null, "place": null, "contributors": null, "is_quote_status": false, "retweet_count": 1, "favorite_count": 10, "favorited": false, "retweeted": false, "possibly_sensitive": false, "lang": "en"}, "contributors_enabled": false, "is_translator": false, "is_translation_enabled": false, "profile_background_color": "E6E9EB", "profile_background_image_url": "http://abs.twimg.com/images/themes/theme1/bg.png", "profile_background_image_url_https": "https://abs.twimg.com/images/themes/theme1/bg.png", "profile_background_tile": false, "profile_image_url": "http://pbs.twimg.com/profile_images/735242324293210112/H8YfgQHP_normal.jpg", "profile_image_url_https": "https://pbs.twimg.com/profile_images/735242324293210112/H8YfgQHP_normal.jpg", "profile_banner_url": "https://pbs.twimg.com/profile_banners/921398240/1475031293", "profile_link_color": "0084B4", "profile_sidebar_border_color": "FFFFFF", "profile_sidebar_fill_color": "DDEEF6", "profile_text_color": "333333", "profile_use_background_image": false, "has_extended_profile": false, "default_profile": false, "default_profile_image": false, "following": true, "live_following": false, "follow_request_sent": false, "notifications": false, "muting": false, "blocking": false, "blocked_by": false, "translator_type": "none"}, {"id": 85340453, "id_str": "85340453", "name": "Kai Chang", "screen_name": "syntagmatic", "location": "San Francisco", "description": "", "url": "https://t.co/YuVTBKmcCD", "entities": {"url": {"urls": [{"url": "https://t.co/YuVTBKmcCD", "expanded_url": "http://syntagmatic.github.io/", "display_url": "syntagmatic.github.io", "indices": [0, 23]}]}, "description": {"urls": []}}, "protected": false, "followers_count": 1556, "friends_count": 305, "listed_count": 151, "created_at": "Mon Oct 26 15:29:19 +0000 2009", "favourites_count": 1144, "utc_offset": null, "time_zone": null, "geo_enabled": false, "verified": false, "statuses_count": 784, "lang": null, "status": {"created_at": "Thu Aug 29 21:03:20 +0000 2019", "id": 1167180958384046080, "id_str": "1167180958384046080", "text": "RT @kerryrodden: I've been playing with using Perlin noise to distort the pixels in an image, and the results turned out to be much more in\u2026", "truncated": false, "entities": {"hashtags": [], "symbols": [], "user_mentions": [{"screen_name": "kerryrodden", "name": "Kerry Rodden", "id": 20555877, "id_str": "20555877", "indices": [3, 15]}], "urls": []}, "source": "<a href=\"http://klinkerapps.com\" rel=\"nofollow\">Talon Android</a>", "in_reply_to_status_id": null, "in_reply_to_status_id_str": null, "in_reply_to_user_id": null, "in_reply_to_user_id_str": null, "in_reply_to_screen_name": null, "geo": null, "coordinates": null, "place": null, "contributors": null, "retweeted_status": {"created_at": "Wed Aug 07 16:29:25 +0000 2019", "id": 1159139494337175552, "id_str": "1159139494337175552", "text": "I've been playing with using Perlin noise to distort the pixels in an image, and the results turned out to be much\u2026 https://t.co/3uTBVg1ShR", "truncated": true, "entities": {"hashtags": [], "symbols": [], "user_mentions": [], "urls": [{"url": "https://t.co/3uTBVg1ShR", "expanded_url": "https://twitter.com/i/web/status/1159139494337175552", "display_url": "twitter.com/i/web/status/1\u2026", "indices": [116, 139]}]}, "source": "<a href=\"https://mobile.twitter.com\" rel=\"nofollow\">Twitter Web App</a>", "in_reply_to_status_id": null, "in_reply_to_status_id_str": null, "in_reply_to_user_id": null, "in_reply_to_user_id_str": null, "in_reply_to_screen_name": null, "geo": null, "coordinates": null, "place": null, "contributors": null, "is_quote_status": false, "retweet_count": 4, "favorite_count": 27, "favorited": false, "retweeted": false, "possibly_sensitive": false, "lang": "en"}, "is_quote_status": false, "retweet_count": 4, "favorite_count": 0, "favorited": false, "retweeted": false, "lang": "en"}, "contributors_enabled": false, "is_translator": false, "is_translation_enabled": false, "profile_background_color": "C0DEED", "profile_background_image_url": "http://abs.twimg.com/images/themes/theme1/bg.png", "profile_background_image_url_https": "https://abs.twimg.com/images/themes/theme1/bg.png", "profile_background_tile": false, "profile_image_url": "http://pbs.twimg.com/profile_images/767900641855279106/lC-KlGyo_normal.jpg", "profile_image_url_https": "https://pbs.twimg.com/profile_images/767900641855279106/lC-KlGyo_normal.jpg", "profile_banner_url": "https://pbs.twimg.com/profile_banners/85340453/1463180432", "profile_link_color": "1DA1F2", "profile_sidebar_border_color": "C0DEED", "profile_sidebar_fill_color": "DDEEF6", "profile_text_color": "333333", "profile_use_background_image": true, "has_extended_profile": false, "default_profile": true, "default_profile_image": false, "following": true, "live_following": false, "follow_request_sent": false, "notifications": false, "muting": false, "blocking": false, "blocked_by": false, "translator_type": "none"}, {"id": 9434762, "id_str": "9434762", "name": "Kanit Ham Wong", "screen_name": "kanitw", "location": "Seattle", "description": "Visualization+Design for Machine Learning @Apple. Co-author of Vega-Lite, Voyager, and TensorFlow Graph Visualizer. Formerly @uwdata. Views are my own.", "url": null, "entities": {"description": {"urls": []}}, "protected": false, "followers_count": 1654, "friends_count": 770, "listed_count": 75, "created_at": "Sun Oct 14 08:33:39 +0000 2007", "favourites_count": 1094, "utc_offset": null, "time_zone": null, "geo_enabled": true, "verified": false, "statuses_count": 2930, "lang": null, "status": {"created_at": "Sat Sep 21 17:07:03 +0000 2019", "id": 1175456415571296256, "id_str": "1175456415571296256", "text": "@amyxzh Haha welcome!", "truncated": false, "entities": {"hashtags": [], "symbols": [], "user_mentions": [{"screen_name": "amyxzh", "name": "Amy X Zhang", "id": 330151669, "id_str": "330151669", "indices": [0, 7]}], "urls": []}, "source": "<a href=\"http://twitter.com/download/iphone\" rel=\"nofollow\">Twitter for iPhone</a>", "in_reply_to_status_id": 1175150437584003075, "in_reply_to_status_id_str": "1175150437584003075", "in_reply_to_user_id": 330151669, "in_reply_to_user_id_str": "330151669", "in_reply_to_screen_name": "amyxzh", "geo": null, "coordinates": null, "place": null, "contributors": null, "is_quote_status": false, "retweet_count": 0, "favorite_count": 1, "favorited": false, "retweeted": false, "lang": "en"}, "contributors_enabled": false, "is_translator": false, "is_translation_enabled": false, "profile_background_color": "000000", "profile_background_image_url": "http://abs.twimg.com/images/themes/theme13/bg.gif", "profile_background_image_url_https": "https://abs.twimg.com/images/themes/theme13/bg.gif", "profile_background_tile": false, "profile_image_url": "http://pbs.twimg.com/profile_images/1130215014474797056/nEoJ4Y8p_normal.jpg", "profile_image_url_https": "https://pbs.twimg.com/profile_images/1130215014474797056/nEoJ4Y8p_normal.jpg", "profile_banner_url": "https://pbs.twimg.com/profile_banners/9434762/1414365427", "profile_link_color": "1B95E0", "profile_sidebar_border_color": "000000", "profile_sidebar_fill_color": "000000", "profile_text_color": "000000", "profile_use_background_image": false, "has_extended_profile": false, "default_profile": false, "default_profile_image": false, "following": true, "live_following": false, "follow_request_sent": false, "notifications": false, "muting": false, "blocking": false, "blocked_by": false, "translator_type": "none"}, {"id": 27241881, "id_str": "27241881", "name": "Ben Nuttall", "screen_name": "ben_nuttall", "location": "Cambridge, UK", "description": "Programme Technical Manager at the @Raspberry_Pi Foundation. @opensourceway columnist. Into Python and Linux. Creator of GPIO Zero and @piwheels.", "url": "https://t.co/Tj0qpQSsGy", "entities": {"url": {"urls": [{"url": "https://t.co/Tj0qpQSsGy", "expanded_url": "https://bennuttall.com", "display_url": "bennuttall.com", "indices": [0, 23]}]}, "description": {"urls": []}}, "protected": false, "followers_count": 9303, "friends_count": 752, "listed_count": 431, "created_at": "Sat Mar 28 15:00:50 +0000 2009", "favourites_count": 16174, "utc_offset": null, "time_zone": null, "geo_enabled": true, "verified": false, "statuses_count": 77067, "lang": null, "status": {"created_at": "Wed Oct 02 15:52:40 +0000 2019", "id": 1179423965732855809, "id_str": "1179423965732855809", "text": "RT @EU_Commission: Your freedom of movement is more than a fundamental right.\n\nIt\u2019s also a reality enjoyed by millions of Europeans. \n\nWe p\u2026", "truncated": false, "entities": {"hashtags": [], "symbols": [], "user_mentions": [{"screen_name": "EU_Commission", "name": "European Commission \ud83c\uddea\ud83c\uddfa", "id": 157981564, "id_str": "157981564", "indices": [3, 17]}], "urls": []}, "source": "<a href=\"http://twitter.com/download/android\" rel=\"nofollow\">Twitter for Android</a>", "in_reply_to_status_id": null, "in_reply_to_status_id_str": null, "in_reply_to_user_id": null, "in_reply_to_user_id_str": null, "in_reply_to_screen_name": null, "geo": null, "coordinates": null, "place": null, "contributors": null, "retweeted_status": {"created_at": "Wed Oct 02 06:32:03 +0000 2019", "id": 1179282879647498240, "id_str": "1179282879647498240", "text": "Your freedom of movement is more than a fundamental right.\n\nIt\u2019s also a reality enjoyed by millions of Europeans.\u2026 https://t.co/zjoxyGQAYz", "truncated": true, "entities": {"hashtags": [], "symbols": [], "user_mentions": [], "urls": [{"url": "https://t.co/zjoxyGQAYz", "expanded_url": "https://twitter.com/i/web/status/1179282879647498240", "display_url": "twitter.com/i/web/status/1\u2026", "indices": [115, 138]}]}, "source": "<a href=\"http://twitter.com/download/iphone\" rel=\"nofollow\">Twitter for iPhone</a>", "in_reply_to_status_id": null, "in_reply_to_status_id_str": null, "in_reply_to_user_id": null, "in_reply_to_user_id_str": null, "in_reply_to_screen_name": null, "geo": null, "coordinates": null, "place": null, "contributors": null, "is_quote_status": false, "retweet_count": 973, "favorite_count": 2066, "favorited": false, "retweeted": false, "possibly_sensitive": false, "lang": "en"}, "is_quote_status": false, "retweet_count": 973, "favorite_count": 0, "favorited": false, "retweeted": false, "lang": "en"}, "contributors_enabled": false, "is_translator": false, "is_translation_enabled": false, "profile_background_color": "131516", "profile_background_image_url": "http://abs.twimg.com/images/themes/theme8/bg.gif", "profile_background_image_url_https": "https://abs.twimg.com/images/themes/theme8/bg.gif", "profile_background_tile": true, "profile_image_url": "http://pbs.twimg.com/profile_images/528155792013160448/cobxlRc8_normal.jpeg", "profile_image_url_https": "https://pbs.twimg.com/profile_images/528155792013160448/cobxlRc8_normal.jpeg", "profile_banner_url": "https://pbs.twimg.com/profile_banners/27241881/1398355496", "profile_link_color": "0091FF", "profile_sidebar_border_color": "EEEEEE", "profile_sidebar_fill_color": "EFEFEF", "profile_text_color": "333333", "profile_use_background_image": true, "has_extended_profile": true, "default_profile": false, "default_profile_image": false, "following": true, "live_following": false, "follow_request_sent": false, "notifications": false, "muting": false, "blocking": false, "blocked_by": false, "translator_type": "none"}], "next_cursor": 1532582667212088252, "next_cursor_str": "1532582667212088252", "previous_cursor": -1533625553401013717, "previous_cursor_str": "-1533625553401013717", "total_count": null}